ximinf/__init__.py
ximinf/generate_sim.py
ximinf/nn_inference.py
ximinf/nn_test.py
ximinf/nn_train.py
ximinf/selection_effects.py
ximinf-0.0.10.dist-info/licenses/LICENSE
ximinf-0.0.10.dist-info/METADATA
ximinf-0.0.10.dist-info/WHEEL
ximinf-0.0.10.dist-info/top_level.txt
ximinf-0.0.10.dist-info/RECORD
